infirunner/__init__.py
infirunner/capsule.py
infirunner/clean.py
infirunner/clean_saves.py
infirunner/generator.py
infirunner/hyperband.py
infirunner/param.py
infirunner/stats.py
infirunner/steppers.py
infirunner/supervisor.py
infirunner/util.py
infirunner/watch.py
infirunner-0.0.1.dist-info/LICENSE
infirunner-0.0.1.dist-info/METADATA
infirunner-0.0.1.dist-info/WHEEL
infirunner-0.0.1.dist-info/top_level.txt
infirunner-0.0.1.dist-info/RECORD
